odoo/addons/mrp_tag/README.rst
odoo/addons/mrp_tag/__init__.py
odoo/addons/mrp_tag/__manifest__.py
odoo/addons/mrp_tag/i18n/es.po
odoo/addons/mrp_tag/i18n/fr.po
odoo/addons/mrp_tag/i18n/hr.po
odoo/addons/mrp_tag/i18n/it.po
odoo/addons/mrp_tag/i18n/mrp_tag.pot
odoo/addons/mrp_tag/i18n/pt_BR.po
odoo/addons/mrp_tag/models/__init__.py
odoo/addons/mrp_tag/models/mrp_production.py
odoo/addons/mrp_tag/models/mrp_tag.py
odoo/addons/mrp_tag/readme/CONTRIBUTORS.md
odoo/addons/mrp_tag/readme/DESCRIPTION.md
odoo/addons/mrp_tag/readme/USAGE.md
odoo/addons/mrp_tag/security/ir.model.access.csv
odoo/addons/mrp_tag/static/description/icon.png
odoo/addons/mrp_tag/static/description/index.html
odoo/addons/mrp_tag/views/mrp_production_view.xml
odoo/addons/mrp_tag/views/mrp_tag_view.xml
odoo_addon_mrp_tag-18.0.1.0.0.7.dist-info/METADATA
odoo_addon_mrp_tag-18.0.1.0.0.7.dist-info/WHEEL
odoo_addon_mrp_tag-18.0.1.0.0.7.dist-info/top_level.txt
odoo_addon_mrp_tag-18.0.1.0.0.7.dist-info/RECORD
